agview/__init__.py
agview/data_list.py
agview-0.0.2.dist-info/METADATA
agview-0.0.2.dist-info/WHEEL
agview-0.0.2.dist-info/top_level.txt
agview-0.0.2.dist-info/RECORD
