Metadata-Version: 2.1
Name: agview
Version: 0.0.2
Summary: Python package for agecoclim
Home-page: UNKNOWN
Author: Park Joo-hyeon
Author-email: www.jrr.kr@gmail.com
License: UNKNOWN
Keywords: microclimate,agecoclim
Platform: UNKNOWN
Classifier: Programming Language :: Python :: 3
Classifier: Programming Language :: Python :: 3.2
Classifier: Programming Language :: Python :: 3.3
Classifier: Programming Language :: Python :: 3.4
Classifier: Programming Language :: Python :: 3.5
Classifier: Programming Language :: Python :: 3.6
Classifier: Programming Language :: Python :: 3.8
Requires-Python: >=3
Requires-Dist: python-dateutil
